meteole/__init__.py
meteole/_arome.py
meteole/_arome_ensemble.py
meteole/_arome_instantane.py
meteole/_arpege.py
meteole/_arpege_ensemble.py
meteole/_piaf.py
meteole/_vigilance.py
meteole/clients.py
meteole/errors.py
meteole/forecast.py
meteole/py.typed
meteole-0.2.4.dist-info/licenses/LICENCE
meteole-0.2.4.dist-info/licenses/NOTICE
meteole-0.2.4.dist-info/METADATA
meteole-0.2.4.dist-info/WHEEL
meteole-0.2.4.dist-info/top_level.txt
meteole-0.2.4.dist-info/RECORD
