Metadata-Version: 2.4
Name: meteole
Version: 0.2.4
Summary: A Python client library for forecast model APIs (e.g., Météo-France).
Author: ThomasBouche, GratienDSX
License: Apache-2.0
Project-URL: Homepage, https://maif.github.io/meteole/
Project-URL: Documentation, https://maif.github.io/meteole/home
Project-URL: Repository, https://github.com/MAIF/meteole
Classifier: Development Status :: 4 - Beta
Classifier: Operating System :: OS Independent
Classifier: Intended Audience :: Developers
Classifier: Intended Audience :: Information Technology
Classifier: Topic :: Software Development :: Libraries :: Python Modules
Classifier: Programming Language :: Python
Classifier: Programming Language :: Python :: 3
Classifier: Programming Language :: Python :: 3 :: Only
Classifier: Programming Language :: Python :: 3.9
Classifier: Programming Language :: Python :: 3.10
Classifier: Programming Language :: Python :: 3.11
Classifier: Programming Language :: Python :: 3.12
Classifier: Programming Language :: Python :: 3.13
Classifier: License :: OSI Approved :: Apache Software License
Requires-Python: >3.8.0
License-File: LICENCE
License-File: NOTICE
Requires-Dist: pandas>=2.0.0
Requires-Dist: eccodes>=2.39.0
Requires-Dist: cfgrib>=0.9.10.4
Requires-Dist: requests>=2.31.0
Requires-Dist: xarray>=2024.5.0
Requires-Dist: xmltodict>=0.13.0
Requires-Dist: matplotlib>=3.8.4
Provides-Extra: test
Requires-Dist: pytest; extra == "test"
Requires-Dist: coverage; extra == "test"
Requires-Dist: tox; extra == "test"
Provides-Extra: doc
Requires-Dist: mkdocs-material; extra == "doc"
Requires-Dist: mkdocstrings[python]; extra == "doc"
Provides-Extra: dev
Requires-Dist: mypy; extra == "dev"
Requires-Dist: pre-commit; extra == "dev"
Requires-Dist: ruff; extra == "dev"
Provides-Extra: all
Requires-Dist: meteole[dev,doc,test]; extra == "all"
Dynamic: license-file
